src/alu.v
module alu #(parameter WIDTH = 4)(

    input [WIDTH-1:0] A,
    input [WIDTH-1:0] B,
    input [2:0] opcode,

    output reg [WIDTH-1:0] result,
    output reg carry,
    output reg zero,
    output reg negative,
    output reg overflow

);

reg [WIDTH:0] temp;

always @(*) begin

    result = 0;
    carry = 0;
    zero = 0;
    negative = 0;
    overflow = 0;
    temp = 0;

    case(opcode)

        // ADD
        3'b000: begin
            temp = A + B;
            result = temp[WIDTH-1:0];
            carry = temp[WIDTH];

            overflow =
                (~A[WIDTH-1] & ~B[WIDTH-1] & result[WIDTH-1]) |
                ( A[WIDTH-1] &  B[WIDTH-1] & ~result[WIDTH-1]);
        end

        // SUB
        3'b001: begin
            temp = A - B;
            result = temp[WIDTH-1:0];
            carry = temp[WIDTH];

            overflow =
                (~A[WIDTH-1] & B[WIDTH-1] & result[WIDTH-1]) |
                ( A[WIDTH-1] & ~B[WIDTH-1] & ~result[WIDTH-1]);
        end

        // AND
        3'b010:
            result = A & B;

        // OR
        3'b011:
            result = A | B;

        // XOR
        3'b100:
            result = A ^ B;

        // NOT
        3'b101:
            result = ~A;

        // SHIFT LEFT
        3'b110:
            result = A << 1;

        // SHIFT RIGHT
        3'b111:
            result = A >> 1;

        default:
            result = 0;

    endcase

    zero = (result == 0);
    negative = result[WIDTH-1];

end

endmodule

tb/alu_tb.v
module alu_tb;

parameter WIDTH = 8;

reg [WIDTH-1:0] A;
reg [WIDTH-1:0] B;
reg [2:0] opcode;

wire [WIDTH-1:0] result;
wire carry;
wire zero;
wire negative;
wire overflow;

alu #(WIDTH) uut (

    .A(A),
    .B(B),
    .opcode(opcode),

    .result(result),
    .carry(carry),
    .zero(zero),
    .negative(negative),
    .overflow(overflow)

);

initial begin

    // Generate waveform
    $dumpfile("sim/alu.vcd");
    $dumpvars(0, alu_tb);

    $display("\n==============================");
    $display("SELF CHECKING TESTBENCH");
    $display("==============================\n");

    //---------------- ADD ----------------

    A = 8'd25;
    B = 8'd17;
    opcode = 3'b000;
    #10;

    if(result == 42)
        $display("ADD Test ........ PASS");
    else
        $display("ADD Test ........ FAIL");

    //---------------- SUB ----------------

    opcode = 3'b001;
    #10;

    if(result == 8)
        $display("SUB Test ........ PASS");
    else
        $display("SUB Test ........ FAIL");

    //---------------- AND ----------------

    A = 8'b11001100;
    B = 8'b10101010;
    opcode = 3'b010;
    #10;

    if(result == 8'b10001000)
        $display("AND Test ........ PASS");
    else
        $display("AND Test ........ FAIL");

    //---------------- OR ----------------

    opcode = 3'b011;
    #10;

    if(result == 8'b11101110)
        $display("OR Test ......... PASS");
    else
        $display("OR Test ......... FAIL");

    //---------------- XOR ----------------

    opcode = 3'b100;
    #10;

    if(result == 8'b01100110)
        $display("XOR Test ........ PASS");
    else
        $display("XOR Test ........ FAIL");

    //---------------- NOT ----------------

    opcode = 3'b101;
    #10;

    if(result == 8'b00110011)
        $display("NOT Test ........ PASS");
    else
        $display("NOT Test ........ FAIL");

    //---------------- SHIFT LEFT ----------------

    A = 8'b00001111;
    opcode = 3'b110;
    #10;

    if(result == 8'b00011110)
        $display("SHL Test ........ PASS");
    else
        $display("SHL Test ........ FAIL");

    //---------------- SHIFT RIGHT ----------------

    A = 8'b11110000;
    opcode = 3'b111;
    #10;

    if(result == 8'b01111000)
        $display("SHR Test ........ PASS");
    else
        $display("SHR Test ........ FAIL");

    //---------------- OVERFLOW ----------------

    A = 8'b01111111;
    B = 8'b00000001;
    opcode = 3'b000;
    #10;

    if(overflow)
        $display("Overflow Test ... PASS");
    else
        $display("Overflow Test ... FAIL");

    $display("\n==============================");
    $display("All tests completed.");
    $display("==============================");

    $finish;

end

endmodule

sim/alu.vcd
$date
	Sun Aug 02 15:30:55 2026
$end
$version
	Icarus Verilog
$end
$timescale
	1s
$end
$scope module alu_tb $end
$var wire 1 ! zero $end
$var wire 8 " result [7:0] $end
$var wire 1 # overflow $end
$var wire 1 $ negative $end
$var wire 1 % carry $end
$var parameter 32 & WIDTH $end
$var reg 8 ' A [7:0] $end
$var reg 8 ( B [7:0] $end
$var reg 3 ) opcode [2:0] $end
$scope module uut $end
$var wire 8 * A [7:0] $end
$var wire 8 + B [7:0] $end
$var wire 3 , opcode [2:0] $end
$var parameter 32 - WIDTH $end
$var reg 1 % carry $end
$var reg 1 $ negative $end
$var reg 1 # overflow $end
$var reg 8 . result [7:0] $end
$var reg 9 / temp [8:0] $end
$var reg 1 ! zero $end
$upscope $end
$upscope $end
$enddefinitions $end
$comment Show the parameter values. $end
$dumpall
b1000 -
b1000 &
$end
#0
$dumpvars
b101010 /
b101010 .
b0 ,
b10001 +
b11001 *
b0 )
b10001 (
b11001 '
0%
0$
0#
b101010 "
0!
$end
#10
b1000 /
b1000 "
b1000 .
b1 )
b1 ,
#20
1$
b0 /
b10001000 "
b10001000 .
b10 )
b10 ,
b10101010 (
b10101010 +
b11001100 '
b11001100 *
#30
1$
b11101110 "
b11101110 .
b11 )
b11 ,
#40
0$
b1100110 "
b1100110 .
b100 )
b100 ,
#50
b110011 "
b110011 .
b101 )
b101 ,
#60
b11110 "
b11110 .
b110 )
b110 ,
b1111 '
b1111 *
#70
b1111000 "
b1111000 .
b111 )
b111 ,
b11110000 '
b11110000 *
#80
1$
1#
b10000000 /
b10000000 "
b10000000 .
b0 )
b0 ,
b1 (
b1 +
b1111111 '
b1111111 *
